{
  "drops": [],
  "bonuses": {
    "2919": [
      200,
      0,
      0,
      200,
      0,
      100,
      0,
      0,
      80,
      100
    ]
  },
  "combatDefinitions": {
    "2919": {
      "hitpoints": 1000,
      "attackAnim": -1,
      "defenceAnim": 65,
      "deathAnim": 67,
      "attackDelay": 6,
      "deathDelay": 4,
      "respawnDelay": 50,
      "maxHit": 100,
      "attackStyle": 0,
      "attackGfx": -1,
      "attackProjectile": -1,
      "aggressivenessType": 0
    }
  },
  "charmDrops": []
}