{
  "drops": [],
  "bonuses": {
    "103": [
      15,
      0,
      0,
      0,
      0,
      15,
      0,
      0,
      15,
      15
    ],
    "104": [
      15,
      0,
      0,
      0,
      0,
      15,
      0,
      0,
      15,
      15
    ],
    "5342": [
      15,
      0,
      0,
      0,
      0,
      15,
      0,
      0,
      15,
      15
    ],
    "5343": [
      15,
      0,
      0,
      0,
      0,
      15,
      0,
      0,
      15,
      15
    ],
    "5344": [
      15,
      0,
      0,
      0,
      0,
      15,
      0,
      0,
      15,
      15
    ],
    "5345": [
      15,
      0,
      0,
      0,
      0,
      15,
      0,
      0,
      15,
      15
    ],
    "5346": [
      15,
      0,
      0,
      0,
      0,
      15,
      0,
      0,
      15,
      15
    ],
    "5347": [
      15,
      0,
      0,
      0,
      0,
      15,
      0,
      0,
      15,
      15
    ],
    "5348": [
      15,
      0,
      0,
      0,
      0,
      15,
      0,
      0,
      15,
      15
    ],
    "5349": [
      15,
      0,
      0,
      0,
      0,
      15,
      0,
      0,
      15,
      15
    ],
    "5350": [
      15,
      0,
      0,
      0,
      0,
      15,
      0,
      0,
      15,
      15
    ],
    "5351": [
      15,
      0,
      0,
      0,
      0,
      15,
      0,
      0,
      15,
      15
    ],
    "5352": [
      15,
      0,
      0,
      0,
      0,
      15,
      0,
      0,
      15,
      15
    ],
    "6094": [
      15,
      0,
      0,
      0,
      0,
      15,
      0,
      0,
      15,
      15
    ],
    "6095": [
      15,
      0,
      0,
      0,
      0,
      15,
      0,
      0,
      15,
      15
    ],
    "6096": [
      15,
      0,
      0,
      0,
      0,
      15,
      0,
      0,
      15,
      15
    ],
    "6097": [
      15,
      0,
      0,
      0,
      0,
      15,
      0,
      0,
      15,
      15
    ],
    "6098": [
      15,
      0,
      0,
      0,
      0,
      15,
      0,
      0,
      15,
      15
    ]
  },
  "combatDefinitions": {
    "103": {
      "hitpoints": 150,
      "attackAnim": 5535,
      "defenceAnim": 5536,
      "deathAnim": 5546,
      "attackDelay": 4,
      "deathDelay": 4,
      "respawnDelay": 50,
      "maxHit": 20,
      "attackStyle": 0,
      "attackGfx": -1,
      "attackProjectile": -1,
      "aggressivenessType": 0
    },
    "104": {
      "hitpoints": 150,
      "attackAnim": 5535,
      "defenceAnim": 5536,
      "deathAnim": 5546,
      "attackDelay": 4,
      "deathDelay": 4,
      "respawnDelay": 50,
      "maxHit": 20,
      "attackStyle": 0,
      "attackGfx": -1,
      "attackProjectile": -1,
      "aggressivenessType": 0
    },
    "4387": {
      "hitpoints": 1,
      "attackAnim": -1,
      "defenceAnim": -1,
      "deathAnim": -1,
      "attackDelay": 5,
      "deathDelay": 4,
      "respawnDelay": 50,
      "maxHit": 1,
      "attackStyle": 0,
      "attackGfx": -1,
      "attackProjectile": -1,
      "aggressivenessType": 0
    },
    "4388": {
      "hitpoints": 1,
      "attackAnim": -1,
      "defenceAnim": -1,
      "deathAnim": -1,
      "attackDelay": 5,
      "deathDelay": 4,
      "respawnDelay": 50,
      "maxHit": 1,
      "attackStyle": 0,
      "attackGfx": -1,
      "attackProjectile": -1,
      "aggressivenessType": 0
    },
    "491": {
      "hitpoints": 1,
      "attackAnim": -1,
      "defenceAnim": -1,
      "deathAnim": -1,
      "attackDelay": 5,
      "deathDelay": 4,
      "respawnDelay": 50,
      "maxHit": 1,
      "attackStyle": 0,
      "attackGfx": -1,
      "attackProjectile": -1,
      "aggressivenessType": 0
    },
    "5342": {
      "hitpoints": 150,
      "attackAnim": 5535,
      "defenceAnim": 5536,
      "deathAnim": 5546,
      "attackDelay": 4,
      "deathDelay": 4,
      "respawnDelay": 50,
      "maxHit": 20,
      "attackStyle": 0,
      "attackGfx": -1,
      "attackProjectile": -1,
      "aggressivenessType": 0
    },
    "5343": {
      "hitpoints": 150,
      "attackAnim": 5535,
      "defenceAnim": 5536,
      "deathAnim": 5546,
      "attackDelay": 4,
      "deathDelay": 4,
      "respawnDelay": 50,
      "maxHit": 20,
      "attackStyle": 0,
      "attackGfx": -1,
      "attackProjectile": -1,
      "aggressivenessType": 0
    },
    "5344": {
      "hitpoints": 150,
      "attackAnim": 5535,
      "defenceAnim": 5536,
      "deathAnim": 5546,
      "attackDelay": 4,
      "deathDelay": 4,
      "respawnDelay": 50,
      "maxHit": 20,
      "attackStyle": 0,
      "attackGfx": -1,
      "attackProjectile": -1,
      "aggressivenessType": 0
    },
    "5345": {
      "hitpoints": 150,
      "attackAnim": 5535,
      "defenceAnim": 5536,
      "deathAnim": 5546,
      "attackDelay": 4,
      "deathDelay": 4,
      "respawnDelay": 50,
      "maxHit": 20,
      "attackStyle": 0,
      "attackGfx": -1,
      "attackProjectile": -1,
      "aggressivenessType": 0
    },
    "5346": {
      "hitpoints": 150,
      "attackAnim": 5535,
      "defenceAnim": 5536,
      "deathAnim": 5546,
      "attackDelay": 4,
      "deathDelay": 4,
      "respawnDelay": 50,
      "maxHit": 20,
      "attackStyle": 0,
      "attackGfx": -1,
      "attackProjectile": -1,
      "aggressivenessType": 0
    },
    "5347": {
      "hitpoints": 150,
      "attackAnim": 5535,
      "defenceAnim": 5536,
      "deathAnim": 5546,
      "attackDelay": 4,
      "deathDelay": 4,
      "respawnDelay": 50,
      "maxHit": 20,
      "attackStyle": 0,
      "attackGfx": -1,
      "attackProjectile": -1,
      "aggressivenessType": 0
    },
    "5348": {
      "hitpoints": 150,
      "attackAnim": 5535,
      "defenceAnim": 5536,
      "deathAnim": 5546,
      "attackDelay": 4,
      "deathDelay": 4,
      "respawnDelay": 50,
      "maxHit": 20,
      "attackStyle": 0,
      "attackGfx": -1,
      "attackProjectile": -1,
      "aggressivenessType": 0
    },
    "5349": {
      "hitpoints": 150,
      "attackAnim": 5535,
      "defenceAnim": 5536,
      "deathAnim": 5546,
      "attackDelay": 4,
      "deathDelay": 4,
      "respawnDelay": 50,
      "maxHit": 20,
      "attackStyle": 0,
      "attackGfx": -1,
      "attackProjectile": -1,
      "aggressivenessType": 0
    },
    "5350": {
      "hitpoints": 150,
      "attackAnim": 5535,
      "defenceAnim": 5536,
      "deathAnim": 5546,
      "attackDelay": 4,
      "deathDelay": 4,
      "respawnDelay": 50,
      "maxHit": 20,
      "attackStyle": 0,
      "attackGfx": -1,
      "attackProjectile": -1,
      "aggressivenessType": 0
    },
    "5351": {
      "hitpoints": 150,
      "attackAnim": 5535,
      "defenceAnim": 5536,
      "deathAnim": 5546,
      "attackDelay": 4,
      "deathDelay": 4,
      "respawnDelay": 50,
      "maxHit": 20,
      "attackStyle": 0,
      "attackGfx": -1,
      "attackProjectile": -1,
      "aggressivenessType": 0
    },
    "5352": {
      "hitpoints": 150,
      "attackAnim": 5535,
      "defenceAnim": 5536,
      "deathAnim": 5546,
      "attackDelay": 4,
      "deathDelay": 4,
      "respawnDelay": 50,
      "maxHit": 20,
      "attackStyle": 0,
      "attackGfx": -1,
      "attackProjectile": -1,
      "aggressivenessType": 0
    },
    "5369": {
      "hitpoints": 1,
      "attackAnim": -1,
      "defenceAnim": -1,
      "deathAnim": -1,
      "attackDelay": 5,
      "deathDelay": 4,
      "respawnDelay": 50,
      "maxHit": 1,
      "attackStyle": 0,
      "attackGfx": -1,
      "attackProjectile": -1,
      "aggressivenessType": 0
    },
    "5370": {
      "hitpoints": 1,
      "attackAnim": -1,
      "defenceAnim": -1,
      "deathAnim": -1,
      "attackDelay": 5,
      "deathDelay": 4,
      "respawnDelay": 50,
      "maxHit": 1,
      "attackStyle": 0,
      "attackGfx": -1,
      "attackProjectile": -1,
      "aggressivenessType": 0
    },
    "5371": {
      "hitpoints": 1,
      "attackAnim": -1,
      "defenceAnim": -1,
      "deathAnim": -1,
      "attackDelay": 5,
      "deathDelay": 4,
      "respawnDelay": 50,
      "maxHit": 1,
      "attackStyle": 0,
      "attackGfx": -1,
      "attackProjectile": -1,
      "aggressivenessType": 0
    },
    "1549": {
      "hitpoints": 1,
      "attackAnim": -1,
      "defenceAnim": -1,
      "deathAnim": -1,
      "attackDelay": 5,
      "deathDelay": 4,
      "respawnDelay": 50,
      "maxHit": 1,
      "attackStyle": 0,
      "attackGfx": -1,
      "attackProjectile": -1,
      "aggressivenessType": 0
    },
    "6094": {
      "hitpoints": 150,
      "attackAnim": 5535,
      "defenceAnim": 5536,
      "deathAnim": 5546,
      "attackDelay": 4,
      "deathDelay": 4,
      "respawnDelay": 50,
      "maxHit": 20,
      "attackStyle": 0,
      "attackGfx": -1,
      "attackProjectile": -1,
      "aggressivenessType": 0
    },
    "6095": {
      "hitpoints": 150,
      "attackAnim": 5535,
      "defenceAnim": 5536,
      "deathAnim": 5546,
      "attackDelay": 4,
      "deathDelay": 4,
      "respawnDelay": 50,
      "maxHit": 20,
      "attackStyle": 0,
      "attackGfx": -1,
      "attackProjectile": -1,
      "aggressivenessType": 0
    },
    "6096": {
      "hitpoints": 150,
      "attackAnim": 5535,
      "defenceAnim": 5536,
      "deathAnim": 5546,
      "attackDelay": 4,
      "deathDelay": 4,
      "respawnDelay": 50,
      "maxHit": 20,
      "attackStyle": 0,
      "attackGfx": -1,
      "attackProjectile": -1,
      "aggressivenessType": 0
    },
    "6097": {
      "hitpoints": 150,
      "attackAnim": 5535,
      "defenceAnim": 5536,
      "deathAnim": 5546,
      "attackDelay": 4,
      "deathDelay": 4,
      "respawnDelay": 50,
      "maxHit": 20,
      "attackStyle": 0,
      "attackGfx": -1,
      "attackProjectile": -1,
      "aggressivenessType": 0
    },
    "6098": {
      "hitpoints": 150,
      "attackAnim": 5535,
      "defenceAnim": 5536,
      "deathAnim": 5546,
      "attackDelay": 4,
      "deathDelay": 4,
      "respawnDelay": 50,
      "maxHit": 20,
      "attackStyle": 0,
      "attackGfx": -1,
      "attackProjectile": -1,
      "aggressivenessType": 0
    },
    "10823": {
      "hitpoints": 1,
      "attackAnim": -1,
      "defenceAnim": -1,
      "deathAnim": -1,
      "attackDelay": 5,
      "deathDelay": 4,
      "respawnDelay": 50,
      "maxHit": 1,
      "attackStyle": 0,
      "attackGfx": -1,
      "attackProjectile": -1,
      "aggressivenessType": 0
    },
    "10826": {
      "hitpoints": 1,
      "attackAnim": -1,
      "defenceAnim": -1,
      "deathAnim": -1,
      "attackDelay": 5,
      "deathDelay": 4,
      "respawnDelay": 50,
      "maxHit": 1,
      "attackStyle": 0,
      "attackGfx": -1,
      "attackProjectile": -1,
      "aggressivenessType": 0
    },
    "10985": {
      "hitpoints": 1,
      "attackAnim": -1,
      "defenceAnim": -1,
      "deathAnim": -1,
      "attackDelay": 5,
      "deathDelay": 4,
      "respawnDelay": 50,
      "maxHit": 1,
      "attackStyle": 0,
      "attackGfx": -1,
      "attackProjectile": -1,
      "aggressivenessType": 0
    },
    "10986": {
      "hitpoints": 1,
      "attackAnim": -1,
      "defenceAnim": -1,
      "deathAnim": -1,
      "attackDelay": 5,
      "deathDelay": 4,
      "respawnDelay": 50,
      "maxHit": 1,
      "attackStyle": 0,
      "attackGfx": -1,
      "attackProjectile": -1,
      "aggressivenessType": 0
    },
    "10987": {
      "hitpoints": 1,
      "attackAnim": -1,
      "defenceAnim": -1,
      "deathAnim": -1,
      "attackDelay": 5,
      "deathDelay": 4,
      "respawnDelay": 50,
      "maxHit": 1,
      "attackStyle": 0,
      "attackGfx": -1,
      "attackProjectile": -1,
      "aggressivenessType": 0
    },
    "10988": {
      "hitpoints": 1,
      "attackAnim": -1,
      "defenceAnim": -1,
      "deathAnim": -1,
      "attackDelay": 5,
      "deathDelay": 4,
      "respawnDelay": 50,
      "maxHit": 1,
      "attackStyle": 0,
      "attackGfx": -1,
      "attackProjectile": -1,
      "aggressivenessType": 0
    },
    "10991": {
      "hitpoints": 1,
      "attackAnim": -1,
      "defenceAnim": -1,
      "deathAnim": -1,
      "attackDelay": 5,
      "deathDelay": 4,
      "respawnDelay": 50,
      "maxHit": 1,
      "attackStyle": 0,
      "attackGfx": -1,
      "attackProjectile": -1,
      "aggressivenessType": 0
    },
    "10992": {
      "hitpoints": 1,
      "attackAnim": -1,
      "defenceAnim": -1,
      "deathAnim": -1,
      "attackDelay": 5,
      "deathDelay": 4,
      "respawnDelay": 50,
      "maxHit": 1,
      "attackStyle": 0,
      "attackGfx": -1,
      "attackProjectile": -1,
      "aggressivenessType": 0
    },
    "7998": {
      "hitpoints": 1,
      "attackAnim": -1,
      "defenceAnim": -1,
      "deathAnim": -1,
      "attackDelay": 5,
      "deathDelay": 4,
      "respawnDelay": 50,
      "maxHit": 1,
      "attackStyle": 0,
      "attackGfx": -1,
      "attackProjectile": -1,
      "aggressivenessType": 0
    },
    "7999": {
      "hitpoints": 1,
      "attackAnim": -1,
      "defenceAnim": -1,
      "deathAnim": -1,
      "attackDelay": 5,
      "deathDelay": 4,
      "respawnDelay": 50,
      "maxHit": 1,
      "attackStyle": 0,
      "attackGfx": -1,
      "attackProjectile": -1,
      "aggressivenessType": 0
    },
    "10821": {
      "hitpoints": 1,
      "attackAnim": -1,
      "defenceAnim": -1,
      "deathAnim": -1,
      "attackDelay": 5,
      "deathDelay": 4,
      "respawnDelay": 50,
      "maxHit": 1,
      "attackStyle": 0,
      "attackGfx": -1,
      "attackProjectile": -1,
      "aggressivenessType": 0
    },
    "10981": {
      "hitpoints": 1,
      "attackAnim": -1,
      "defenceAnim": -1,
      "deathAnim": -1,
      "attackDelay": 5,
      "deathDelay": 4,
      "respawnDelay": 50,
      "maxHit": 1,
      "attackStyle": 0,
      "attackGfx": -1,
      "attackProjectile": -1,
      "aggressivenessType": 0
    },
    "10982": {
      "hitpoints": 1,
      "attackAnim": -1,
      "defenceAnim": -1,
      "deathAnim": -1,
      "attackDelay": 5,
      "deathDelay": 4,
      "respawnDelay": 50,
      "maxHit": 1,
      "attackStyle": 0,
      "attackGfx": -1,
      "attackProjectile": -1,
      "aggressivenessType": 0
    },
    "10822": {
      "hitpoints": 1,
      "attackAnim": -1,
      "defenceAnim": -1,
      "deathAnim": -1,
      "attackDelay": 5,
      "deathDelay": 4,
      "respawnDelay": 50,
      "maxHit": 1,
      "attackStyle": 0,
      "attackGfx": -1,
      "attackProjectile": -1,
      "aggressivenessType": 0
    },
    "10983": {
      "hitpoints": 1,
      "attackAnim": -1,
      "defenceAnim": -1,
      "deathAnim": -1,
      "attackDelay": 5,
      "deathDelay": 4,
      "respawnDelay": 50,
      "maxHit": 1,
      "attackStyle": 0,
      "attackGfx": -1,
      "attackProjectile": -1,
      "aggressivenessType": 0
    },
    "10984": {
      "hitpoints": 1,
      "attackAnim": -1,
      "defenceAnim": -1,
      "deathAnim": -1,
      "attackDelay": 5,
      "deathDelay": 4,
      "respawnDelay": 50,
      "maxHit": 1,
      "attackStyle": 0,
      "attackGfx": -1,
      "attackProjectile": -1,
      "aggressivenessType": 0
    },
    "10824": {
      "hitpoints": 1,
      "attackAnim": -1,
      "defenceAnim": -1,
      "deathAnim": -1,
      "attackDelay": 5,
      "deathDelay": 4,
      "respawnDelay": 50,
      "maxHit": 1,
      "attackStyle": 0,
      "attackGfx": -1,
      "attackProjectile": -1,
      "aggressivenessType": 0
    },
    "10825": {
      "hitpoints": 1,
      "attackAnim": -1,
      "defenceAnim": -1,
      "deathAnim": -1,
      "attackDelay": 5,
      "deathDelay": 4,
      "respawnDelay": 50,
      "maxHit": 1,
      "attackStyle": 0,
      "attackGfx": -1,
      "attackProjectile": -1,
      "aggressivenessType": 0
    },
    "10989": {
      "hitpoints": 1,
      "attackAnim": -1,
      "defenceAnim": -1,
      "deathAnim": -1,
      "attackDelay": 5,
      "deathDelay": 4,
      "respawnDelay": 50,
      "maxHit": 1,
      "attackStyle": 0,
      "attackGfx": -1,
      "attackProjectile": -1,
      "aggressivenessType": 0
    },
    "10990": {
      "hitpoints": 1,
      "attackAnim": -1,
      "defenceAnim": -1,
      "deathAnim": -1,
      "attackDelay": 5,
      "deathDelay": 4,
      "respawnDelay": 50,
      "maxHit": 1,
      "attackStyle": 0,
      "attackGfx": -1,
      "attackProjectile": -1,
      "aggressivenessType": 0
    },
    "10827": {
      "hitpoints": 1,
      "attackAnim": -1,
      "defenceAnim": -1,
      "deathAnim": -1,
      "attackDelay": 5,
      "deathDelay": 4,
      "respawnDelay": 50,
      "maxHit": 1,
      "attackStyle": 0,
      "attackGfx": -1,
      "attackProjectile": -1,
      "aggressivenessType": 0
    },
    "10993": {
      "hitpoints": 1,
      "attackAnim": -1,
      "defenceAnim": -1,
      "deathAnim": -1,
      "attackDelay": 5,
      "deathDelay": 4,
      "respawnDelay": 50,
      "maxHit": 1,
      "attackStyle": 0,
      "attackGfx": -1,
      "attackProjectile": -1,
      "aggressivenessType": 0
    },
    "10994": {
      "hitpoints": 1,
      "attackAnim": -1,
      "defenceAnim": -1,
      "deathAnim": -1,
      "attackDelay": 5,
      "deathDelay": 4,
      "respawnDelay": 50,
      "maxHit": 1,
      "attackStyle": 0,
      "attackGfx": -1,
      "attackProjectile": -1,
      "aggressivenessType": 0
    },
    "10828": {
      "hitpoints": 1,
      "attackAnim": -1,
      "defenceAnim": -1,
      "deathAnim": -1,
      "attackDelay": 5,
      "deathDelay": 4,
      "respawnDelay": 50,
      "maxHit": 1,
      "attackStyle": 0,
      "attackGfx": -1,
      "attackProjectile": -1,
      "aggressivenessType": 0
    },
    "10995": {
      "hitpoints": 1,
      "attackAnim": -1,
      "defenceAnim": -1,
      "deathAnim": -1,
      "attackDelay": 5,
      "deathDelay": 4,
      "respawnDelay": 50,
      "maxHit": 1,
      "attackStyle": 0,
      "attackGfx": -1,
      "attackProjectile": -1,
      "aggressivenessType": 0
    },
    "10996": {
      "hitpoints": 1,
      "attackAnim": -1,
      "defenceAnim": -1,
      "deathAnim": -1,
      "attackDelay": 5,
      "deathDelay": 4,
      "respawnDelay": 50,
      "maxHit": 1,
      "attackStyle": 0,
      "attackGfx": -1,
      "attackProjectile": -1,
      "aggressivenessType": 0
    },
    "10997": {
      "hitpoints": 1,
      "attackAnim": -1,
      "defenceAnim": -1,
      "deathAnim": -1,
      "attackDelay": 5,
      "deathDelay": 4,
      "respawnDelay": 50,
      "maxHit": 1,
      "attackStyle": 0,
      "attackGfx": -1,
      "attackProjectile": -1,
      "aggressivenessType": 0
    },
    "10829": {
      "hitpoints": 1,
      "attackAnim": -1,
      "defenceAnim": -1,
      "deathAnim": -1,
      "attackDelay": 5,
      "deathDelay": 4,
      "respawnDelay": 50,
      "maxHit": 1,
      "attackStyle": 0,
      "attackGfx": -1,
      "attackProjectile": -1,
      "aggressivenessType": 0
    },
    "10998": {
      "hitpoints": 1,
      "attackAnim": -1,
      "defenceAnim": -1,
      "deathAnim": -1,
      "attackDelay": 5,
      "deathDelay": 4,
      "respawnDelay": 50,
      "maxHit": 1,
      "attackStyle": 0,
      "attackGfx": -1,
      "attackProjectile": -1,
      "aggressivenessType": 0
    },
    "10830": {
      "hitpoints": 1,
      "attackAnim": -1,
      "defenceAnim": -1,
      "deathAnim": -1,
      "attackDelay": 5,
      "deathDelay": 4,
      "respawnDelay": 50,
      "maxHit": 1,
      "attackStyle": 0,
      "attackGfx": -1,
      "attackProjectile": -1,
      "aggressivenessType": 0
    },
    "10999": {
      "hitpoints": 1,
      "attackAnim": -1,
      "defenceAnim": -1,
      "deathAnim": -1,
      "attackDelay": 5,
      "deathDelay": 4,
      "respawnDelay": 50,
      "maxHit": 1,
      "attackStyle": 0,
      "attackGfx": -1,
      "attackProjectile": -1,
      "aggressivenessType": 0
    },
    "11000": {
      "hitpoints": 1,
      "attackAnim": -1,
      "defenceAnim": -1,
      "deathAnim": -1,
      "attackDelay": 5,
      "deathDelay": 4,
      "respawnDelay": 50,
      "maxHit": 1,
      "attackStyle": 0,
      "attackGfx": -1,
      "attackProjectile": -1,
      "aggressivenessType": 0
    }
  },
  "charmDrops": [
    {
      "itemId": 12158,
      "minAmount": 1,
      "maxAmount": 1,
      "rate": 0.3
    },
    {
      "itemId": 12159,
      "minAmount": 1,
      "maxAmount": 1,
      "rate": 0.2
    },
    {
      "itemId": 12160,
      "minAmount": 1,
      "maxAmount": 1,
      "rate": 0.1
    },
    {
      "itemId": 12163,
      "minAmount": 1,
      "maxAmount": 1,
      "rate": 0.05
    }
  ]
}