{
  "drops": [],
  "bonuses": {},
  "combatDefinitions": {
    "12903": {
      "hitpoints": 1,
      "attackAnim": -1,
      "defenceAnim": -1,
      "deathAnim": -1,
      "attackDelay": 5,
      "deathDelay": 4,
      "respawnDelay": 50,
      "maxHit": 1,
      "attackStyle": 0,
      "attackGfx": -1,
      "attackProjectile": -1,
      "aggressivenessType": 0
    },
    "12904": {
      "hitpoints": 1,
      "attackAnim": -1,
      "defenceAnim": -1,
      "deathAnim": -1,
      "attackDelay": 5,
      "deathDelay": 4,
      "respawnDelay": 50,
      "maxHit": 1,
      "attackStyle": 0,
      "attackGfx": -1,
      "attackProjectile": -1,
      "aggressivenessType": 0
    },
    "12905": {
      "hitpoints": 1,
      "attackAnim": -1,
      "defenceAnim": -1,
      "deathAnim": -1,
      "attackDelay": 5,
      "deathDelay": 4,
      "respawnDelay": 50,
      "maxHit": 1,
      "attackStyle": 0,
      "attackGfx": -1,
      "attackProjectile": -1,
      "aggressivenessType": 0
    },
    "12906": {
      "hitpoints": 1,
      "attackAnim": -1,
      "defenceAnim": -1,
      "deathAnim": -1,
      "attackDelay": 5,
      "deathDelay": 4,
      "respawnDelay": 50,
      "maxHit": 1,
      "attackStyle": 0,
      "attackGfx": -1,
      "attackProjectile": -1,
      "aggressivenessType": 0
    },
    "12907": {
      "hitpoints": 1,
      "attackAnim": -1,
      "defenceAnim": -1,
      "deathAnim": -1,
      "attackDelay": 5,
      "deathDelay": 4,
      "respawnDelay": 50,
      "maxHit": 1,
      "attackStyle": 0,
      "attackGfx": -1,
      "attackProjectile": -1,
      "aggressivenessType": 0
    },
    "12908": {
      "hitpoints": 1,
      "attackAnim": -1,
      "defenceAnim": -1,
      "deathAnim": -1,
      "attackDelay": 5,
      "deathDelay": 4,
      "respawnDelay": 50,
      "maxHit": 1,
      "attackStyle": 0,
      "attackGfx": -1,
      "attackProjectile": -1,
      "aggressivenessType": 0
    },
    "12909": {
      "hitpoints": 1,
      "attackAnim": -1,
      "defenceAnim": -1,
      "deathAnim": -1,
      "attackDelay": 5,
      "deathDelay": 4,
      "respawnDelay": 50,
      "maxHit": 1,
      "attackStyle": 0,
      "attackGfx": -1,
      "attackProjectile": -1,
      "aggressivenessType": 0
    },
    "12910": {
      "hitpoints": 1,
      "attackAnim": -1,
      "defenceAnim": -1,
      "deathAnim": -1,
      "attackDelay": 5,
      "deathDelay": 4,
      "respawnDelay": 50,
      "maxHit": 1,
      "attackStyle": 0,
      "attackGfx": -1,
      "attackProjectile": -1,
      "aggressivenessType": 0
    },
    "12911": {
      "hitpoints": 1,
      "attackAnim": -1,
      "defenceAnim": -1,
      "deathAnim": -1,
      "attackDelay": 5,
      "deathDelay": 4,
      "respawnDelay": 50,
      "maxHit": 1,
      "attackStyle": 0,
      "attackGfx": -1,
      "attackProjectile": -1,
      "aggressivenessType": 0
    },
    "12912": {
      "hitpoints": 1,
      "attackAnim": -1,
      "defenceAnim": -1,
      "deathAnim": -1,
      "attackDelay": 5,
      "deathDelay": 4,
      "respawnDelay": 50,
      "maxHit": 1,
      "attackStyle": 0,
      "attackGfx": -1,
      "attackProjectile": -1,
      "aggressivenessType": 0
    },
    "12913": {
      "hitpoints": 1,
      "attackAnim": -1,
      "defenceAnim": -1,
      "deathAnim": -1,
      "attackDelay": 5,
      "deathDelay": 4,
      "respawnDelay": 50,
      "maxHit": 1,
      "attackStyle": 0,
      "attackGfx": -1,
      "attackProjectile": -1,
      "aggressivenessType": 0
    }
  },
  "charmDrops": []
}