{
  "drops": [
    {
      "itemId": 1295,
      "minAmount": 1,
      "maxAmount": 1,
      "rate": 85.0
    },
    {
      "itemId": 1281,
      "minAmount": 1,
      "maxAmount": 1,
      "rate": 97.0
    },
    {
      "itemId": 1428,
      "minAmount": 1,
      "maxAmount": 1,
      "rate": 77.0
    },
    {
      "itemId": 1257,
      "minAmount": 1,
      "maxAmount": 1,
      "rate": 92.0
    },
    {
      "itemId": 1371,
      "minAmount": 1,
      "maxAmount": 1,
      "rate": 58.0
    },
    {
      "itemId": 1341,
      "minAmount": 1,
      "maxAmount": 1,
      "rate": 73.0
    },
    {
      "itemId": 830,
      "minAmount": 5,
      "maxAmount": 5,
      "rate": 60.0
    },
    {
      "itemId": 1217,
      "minAmount": 1,
      "maxAmount": 1,
      "rate": 60.0
    },
    {
      "itemId": 1355,
      "minAmount": 1,
      "maxAmount": 1,
      "rate": 70.0
    },
    {
      "itemId": 1279,
      "minAmount": 1,
      "maxAmount": 1,
      "rate": 66.0
    },
    {
      "itemId": 1323,
      "minAmount": 1,
      "maxAmount": 1,
      "rate": 62.0
    },
    {
      "itemId": 3202,
      "minAmount": 1,
      "maxAmount": 1,
      "rate": 37.0
    },
    {
      "itemId": 1317,
      "minAmount": 1,
      "maxAmount": 1,
      "rate": 29.0
    },
    {
      "itemId": 1247,
      "minAmount": 1,
      "maxAmount": 1,
      "rate": 26.0
    },
    {
      "itemId": 1303,
      "minAmount": 1,
      "maxAmount": 1,
      "rate": 68.0
    },
    {
      "itemId": 1249,
      "minAmount": 1,
      "maxAmount": 1,
      "rate": 2.0
    },
    {
      "itemId": 1105,
      "minAmount": 1,
      "maxAmount": 1,
      "rate": 92.0
    },
    {
      "itemId": 1161,
      "minAmount": 1,
      "maxAmount": 1,
      "rate": 93.0
    },
    {
      "itemId": 1071,
      "minAmount": 1,
      "maxAmount": 1,
      "rate": 96.0
    },
    {
      "itemId": 1059,
      "minAmount": 1,
      "maxAmount": 1,
      "rate": 94.0
    },
    {
      "itemId": 1195,
      "minAmount": 1,
      "maxAmount": 1,
      "rate": 58.0
    },
    {
      "itemId": 1081,
      "minAmount": 1,
      "maxAmount": 1,
      "rate": 57.0
    },
    {
      "itemId": 1201,
      "minAmount": 1,
      "maxAmount": 1,
      "rate": 27.0
    },
    {
      "itemId": 1623,
      "minAmount": 1,
      "maxAmount": 1,
      "rate": 75.0
    },
    {
      "itemId": 1621,
      "minAmount": 1,
      "maxAmount": 1,
      "rate": 74.0
    },
    {
      "itemId": 1619,
      "minAmount": 1,
      "maxAmount": 1,
      "rate": 71.0
    },
    {
      "itemId": 1617,
      "minAmount": 1,
      "maxAmount": 1,
      "rate": 53.0
    },
    {
      "itemId": 1462,
      "minAmount": 1,
      "maxAmount": 1,
      "rate": 54.0
    },
    {
      "itemId": 2366,
      "minAmount": 1,
      "maxAmount": 1,
      "rate": 3.0
    },
    {
      "itemId": 985,
      "minAmount": 1,
      "maxAmount": 1,
      "rate": 7.0
    },
    {
      "itemId": 987,
      "minAmount": 1,
      "maxAmount": 1,
      "rate": 4.0
    }
  ],
  "bonuses": {
    "6219": [
      120,
      0,
      0,
      0,
      0,
      140,
      0,
      0,
      105,
      148
    ],
    "6277": [
      120,
      0,
      0,
      0,
      0,
      140,
      0,
      0,
      105,
      148
    ],
    "6229": [
      120,
      0,
      0,
      0,
      0,
      140,
      0,
      0,
      105,
      148
    ],
    "6255": [
      120,
      0,
      0,
      0,
      0,
      140,
      0,
      0,
      105,
      148
    ]
  },
  "combatDefinitions": {
    "6255": {
      "hitpoints": 1100,
      "attackAnim": 400,
      "defenceAnim": 398,
      "deathAnim": 2304,
      "attackDelay": 4,
      "deathDelay": 3,
      "respawnDelay": 50,
      "maxHit": 145,
      "attackStyle": 0,
      "attackGfx": -1,
      "attackProjectile": -1,
      "aggressivenessType": 0
    },
    "6219": {
      "hitpoints": 1100,
      "attackAnim": 390,
      "defenceAnim": 398,
      "deathAnim": 2304,
      "attackDelay": 4,
      "deathDelay": 3,
      "respawnDelay": 50,
      "maxHit": 145,
      "attackStyle": 0,
      "attackGfx": -1,
      "attackProjectile": -1,
      "aggressivenessType": 0
    },
    "6277": {
      "hitpoints": 1100,
      "attackAnim": 4320,
      "defenceAnim": 4322,
      "deathAnim": 2304,
      "attackDelay": 4,
      "deathDelay": 3,
      "respawnDelay": 50,
      "maxHit": 145,
      "attackStyle": 0,
      "attackGfx": -1,
      "attackProjectile": -1,
      "aggressivenessType": 0
    },
    "6229": {
      "hitpoints": 1100,
      "attackAnim": 6954,
      "defenceAnim": 6955,
      "deathAnim": 6956,
      "attackDelay": 4,
      "deathDelay": 3,
      "respawnDelay": 50,
      "maxHit": 145,
      "attackStyle": 0,
      "attackGfx": -1,
      "attackProjectile": -1,
      "aggressivenessType": 0
    }
  },
  "charmDrops": [
    {
      "itemId": 12158,
      "minAmount": 1,
      "maxAmount": 12,
      "rate": 0.3
    },
    {
      "itemId": 12159,
      "minAmount": 1,
      "maxAmount": 12,
      "rate": 0.2
    },
    {
      "itemId": 12160,
      "minAmount": 1,
      "maxAmount": 12,
      "rate": 0.1
    },
    {
      "itemId": 12163,
      "minAmount": 1,
      "maxAmount": 12,
      "rate": 0.05
    }
  ]
}